DataQualityFrameworkGovernance/Completeness.py
DataQualityFrameworkGovernance/Datastats.py
DataQualityFrameworkGovernance/__init__.py
DataQualityFrameworkGovernance/test.py
DataQualityFrameworkGovernance-30.10.2023.1.dist-info/LICENSE
DataQualityFrameworkGovernance-30.10.2023.1.dist-info/METADATA
DataQualityFrameworkGovernance-30.10.2023.1.dist-info/WHEEL
DataQualityFrameworkGovernance-30.10.2023.1.dist-info/top_level.txt
DataQualityFrameworkGovernance-30.10.2023.1.dist-info/RECORD
