Metadata-Version: 2.1
Name: DataQualityFrameworkGovernance
Version: 30.10.2023.1
Summary: Data Quality Framework Governance is a structured approach to assessing, monitoring, and improving the quality of data.
Author-email: Rajith Prabhakaran <rajith.prabhakaran@yahoo.com>
Project-URL: Homepage, https://github.com/RajithPrabakaran/DataQualityFrameworkGovernance
Project-URL: Bug Tracker, https://github.com/RajithPrabakaran/DataQualityFrameworkGovernance/issues
Classifier: Programming Language :: Python :: 3
Classifier: License :: OSI Approved :: MIT License
Classifier: Operating System :: OS Independent
Requires-Python: >=3.7
License-File: LICENSE
